README.rst
setup.cfg
setup.py
cp_sqlalchemy/__init__.py
cp_sqlalchemy/plugin.py
cp_sqlalchemy/tool.py
cp_sqlalchemy.egg-info/PKG-INFO
cp_sqlalchemy.egg-info/SOURCES.txt
cp_sqlalchemy.egg-info/dependency_links.txt
cp_sqlalchemy.egg-info/not-zip-safe
cp_sqlalchemy.egg-info/requires.txt
cp_sqlalchemy.egg-info/top_level.txt