Metadata-Version: 1.1
Name: cp-sqlalchemy
Version: 0.5.1
Summary: Use SQLAlchemy with CherryPy
Home-page: https://github.com/ionrock/cp_sqlalchemy
Author: Eric Larson
Author-email: eric@ionrock.org
License: BSD
Keywords: cp_sqlalchemy
Platform: UNKNOWN
Classifier: Development Status :: 2 - Pre-Alpha
Classifier: Intended Audience :: Developers
Classifier: License :: OSI Approved :: BSD License
Classifier: Natural Language :: English
Classifier: Programming Language :: Python :: 2
Classifier: Programming Language :: Python :: 2.6
Classifier: Programming Language :: Python :: 2.7
Classifier: Programming Language :: Python :: 3
Classifier: Programming Language :: Python :: 3.3
Classifier: Programming Language :: Python :: 3.4
